COPYING
LICENSE-gpl-3.0.txt
MANIFEST.in
README
SConstruct
setup.cfg
setup.py
openoffice/ListenerProcAdapters.py
openoffice/__init__.py
openoffice/colors.py
openoffice/config.py
openoffice/datatypes.py
openoffice/dialogs.py
openoffice/interact.py
openoffice/officehelper.py
openoffice/streams.py
openoffice/styles.py
openoffice/windowsListeners.py
openoffice_python.egg-info/PKG-INFO
openoffice_python.egg-info/SOURCES.txt
openoffice_python.egg-info/dependency_links.txt
openoffice_python.egg-info/top_level.txt
sample-scripts/PrintToWriter.py
sample-scripts/check-installation
sample-scripts/odf2pdf.py
sample-scripts/ooo-server
sample-scripts/open-stream.py