Metadata-Version: 1.1
Name: openoffice-python
Version: 0.1-20110209
Summary: Enhanced Python interfaces to OpenOffice.org
Home-page: http://openoffice-python.origo.ethz.ch/
Author: Hartmut Goebel
Author-email: h.goebel@goebel-consult.de
License: GPLv3
Download-URL: http://openoffice-python.origo.ethz.ch/download
Platform: POSIX
Classifier: Development Status :: 4 - Beta
Classifier: Intended Audience :: Developers
Classifier: License :: OSI Approved :: GNU General Public License (GPL)
Classifier: Operating System :: POSIX
Classifier: Programming Language :: Python
Classifier: Topic :: Software Development :: Libraries :: Python Modules
Requires: python(>=2.3)
